sidechannelattack/__init__.py
sidechannelattack/attackmeasure/__init__.py
sidechannelattack/attackmeasure/big_ttest.py
sidechannelattack/attackmeasure/cpa.py
sidechannelattack/attackmeasure/dpa.py
sidechannelattack/attackmeasure/modef_attack.py
sidechannelattack/attackmeasure/model_attack.py
sidechannelattack/attackmeasure/new_math.py
sidechannelattack/attackmeasure/t_testlll.py
sidechannelattack/attackmeasure/models/DES.py
sidechannelattack/attackmeasure/models/__init__.py
sidechannelattack/attackmeasure/models/base.py
sidechannelattack/attackmeasure/models/aes/__init__.py
sidechannelattack/attackmeasure/models/aes/funcs.py
sidechannelattack/attackmeasure/models/aes/key_schedule.py
sidechannelattack/attackmeasure/utils/__init__.py
sidechannelattack/attackmeasure/utils/aes_cipher.py
sidechannelattack/attackmeasure/utils/aes_tables.py
sidechannelattack/attackmeasure/utils/parameter.py
sidechannelattack/attackmeasure/utils/util.py
sidechannelattack/basetrace/__init__.py
sidechannelattack/basetrace/base.py
sidechannelattack/basetrace/data_resolve.py
sidechannelattack/basetrace/get_intermediate_value.py
sidechannelattack/basetrace/new_math.py
sidechannelattack/data_visualization/__init__.py
sidechannelattack/data_visualization/plt_ttest.py
sidechannelattack/data_visualization/test.py
sidechannelattack/leakage_testing/T_test.py
sidechannelattack/leakage_testing/__init__.py
sidechannelattack/leakage_testing/correlation_test.py
sidechannelattack/leakage_testing/snr.py
sidechannelattack/leakage_testing/t-test.py
sidechannelattack/n_leakage_testing/__init__.py
sidechannelattack/n_leakage_testing/correlation.py
sidechannelattack/n_leakage_testing/pre_traces.py
sidechannelattack/n_leakage_testing/snr.py
sidechannelattack/n_leakage_testing/t-test.py
sidechannelattack/pretrace/__init__.py
sidechannelattack/pretrace/aligner.py
sidechannelattack/pretrace/base.py
sidechannelattack/pretrace/demo.py
sidechannelattack/pretrace/fft.py
sidechannelattack/pretrace/filter.py
sidechannelattack-0.0.2.dist-info/LICENSE
sidechannelattack-0.0.2.dist-info/METADATA
sidechannelattack-0.0.2.dist-info/WHEEL
sidechannelattack-0.0.2.dist-info/top_level.txt
sidechannelattack-0.0.2.dist-info/RECORD
